nagini3D/data/data_aug_tools.py
nagini3D/data/intensity_tools.py
nagini3D/data/th_optim_set.py
nagini3D/data/training_set.py
nagini3D/data/format_dataset/data_reading_tools.py
nagini3D/models/model.py
nagini3D/models/loss/sliced_wasserstein_loss.py
nagini3D/models/loss/snake_regularized.py
nagini3D/models/loss/snake_regularized_old.py
nagini3D/models/tools/coordinates.py
nagini3D/models/tools/cost_matrix.py
nagini3D/models/tools/display_val.py
nagini3D/models/tools/image_tools.py
nagini3D/models/tools/inference_tools.py
nagini3D/models/tools/refinement.py
nagini3D/models/tools/snake_sampler.py
nagini3D/models/tools/snake_tools.py
nagini3D/models/unet/u3D_3D.py
nagini3D/models/unet/unet_clean.py
nagini3D/models/unet/internals/layers.py
nagini3d-0.2.2.dist-info/METADATA
nagini3d-0.2.2.dist-info/WHEEL
nagini3d-0.2.2.dist-info/licenses/LICENSE
nagini3d-0.2.2.dist-info/RECORD
